{
  "ProdConfiguration": {
    "rootFolder": "./",
    "pages": 10,
    "mailingList": [
      "gordon.pn6@gmail.com",
      "thanhvan68@hotmail.com"
    ],
    "email Settings": {
      "host": "smtp.gmail.com",
      "port": 587,
      "protocol": "smtp",
      "username": "${GMAIL_USERNAME}",
      "password": "${GMAIL_PASSWORD"
    }
  },
  "TestConfiguration": {
    "rootFolder": "target/resources/",
    "pages": 1,
    "mailingList": [
      "gordon.pn6@gmail.com"
    ],
    "email Settings": {
      "host": "smtp.gmail.com",
      "port": 587,
      "protocol": "smtp",
      "username": "${GMAIL_USERNAME}",
      "password": "${GMAIL_PASSWORD"
    }
  }
}